<?xml version="1.0" encoding="utf-8"?>
<object name="portal_relations" meta_type="EEARelationsTool">


	Content type definitions
	<object name="specification" meta_type="EEARelationsContentType">
		<property name="title">Specification</property>
		<property name="ct_type">Specification</property>
		<property name="ct_interface"></property>
	</object>
	<object name="eea-data" meta_type="EEARelationsContentType">
		<property name="title">EEA Data</property>
		<property name="ct_type">Data</property>
		<property name="ct_interface"></property>
	</object>
	<object name="policy-document-reference" meta_type="EEARelationsContentType">
		<property name="title">Policy Document Reference</property>
		<property name="ct_type">PolicyDocumentReference</property>
		<property name="ct_interface"></property>
	</object>
	<object name="external-data-spec" meta_type="EEARelationsContentType">
		<property name="title">External Data Spec</property>
		<property name="ct_type">ExternalDataSpec</property>
		<property name="ct_interface"></property>
	</object>

	Possible relationships
	<object name="specification-eea-data" meta_type="EEAPossibleRelation">
		<property name="title">Specification -&gt; EEA Data</property>
		<property name="from">specification</property>
		<property name="to">eea-data</property>
		<property name="required">False</property>
	</object>
	<object name="specification-policy-document-reference" meta_type="EEAPossibleRelation">
		<property name="title">Specification -&gt; Policy Document Reference</property>
		<property name="from">specification</property>
		<property name="to">policy-document-reference</property>
		<property name="required">False</property>
	</object>
	<object name="specification-external-data-spec" meta_type="EEAPossibleRelation">
		<property name="title">Specification -&gt; External Data Spec</property>
		<property name="from">specification</property>
		<property name="to">external-data-spec</property>
		<property name="required">False</property>
		<property name="required_for">
			<element value="published"/>
		</property>
	</object>
</object>
